gettranslated_cli/__init__.py
gettranslated_cli/main.py
gettranslated_cli-1.3.1.dist-info/licenses/LICENSE
gettranslated_cli-1.3.1.dist-info/METADATA
gettranslated_cli-1.3.1.dist-info/WHEEL
gettranslated_cli-1.3.1.dist-info/entry_points.txt
gettranslated_cli-1.3.1.dist-info/top_level.txt
gettranslated_cli-1.3.1.dist-info/RECORD
