Metadata-Version: 2.4
Name: gettranslated-cli
Version: 1.3.1
Summary: Command-line tool for syncing translations with GetTranslated.ai
Home-page: https://www.gettranslated.ai
Author: GetTranslated
Author-email: GetTranslated <support@gettranslated.ai>
License: MIT
Project-URL: Documentation, https://www.gettranslated.ai/developers/cli-quickstart/
Keywords: translation,localization,i18n,l10n,cli,android,ios,react-native
Classifier: Development Status :: 4 - Beta
Classifier: Intended Audience :: Developers
Classifier: Topic :: Software Development :: Localization
Classifier: Topic :: Software Development :: Libraries :: Python Modules
Classifier: License :: OSI Approved :: MIT License
Classifier: Programming Language :: Python :: 3
Classifier: Programming Language :: Python :: 3.6
Classifier: Programming Language :: Python :: 3.7
Classifier: Programming Language :: Python :: 3.8
Classifier: Programming Language :: Python :: 3.9
Classifier: Programming Language :: Python :: 3.10
Classifier: Programming Language :: Python :: 3.11
Classifier: Programming Language :: Python :: 3.12
Requires-Python: >=3.6
License-File: LICENSE
Requires-Dist: requests>=2.25.0
Dynamic: author
Dynamic: home-page
Dynamic: license-file
Dynamic: requires-python
